poker_game_engine/__init__.py
poker_game_engine/action_handlers.py
poker_game_engine/constants.py
poker_game_engine/game_engine.py
poker_game_engine/game_logger.py
poker_game_engine/simulator.py
poker_game_engine-0.1.2.dist-info/METADATA
poker_game_engine-0.1.2.dist-info/WHEEL
poker_game_engine-0.1.2.dist-info/RECORD
